{
  "id": "sources-caudalie-guest-relation-juillet-2026",
  "title": "Guest Relation Agent - Réceptionniste H/F",
  "employer": "Les Sources de Caudalie",
  "source_url": "https://www.sources-hotels.com/bordeaux/en/job/",
  "source_site": "sources-hotels.com",
  "source_kind": "direct_employer",
  "verification_status": "active",
  "published_at": "2026-06-22",
  "captured_at": "2026-07-22T16:18:00+02:00",
  "last_verified_at": "2026-07-22T16:18:00+02:00",
  "summary": "Accueillir les clients d'un établissement haut de gamme, assurer la réception, répondre aux demandes et contribuer à une expérience personnalisée.",
  "location_label": "Bordeaux-Martillac",
  "contract_type": "CDD",
  "full_time": true,
  "sector_labels": [
    "luxe",
    "hôtellerie",
    "bien-être"
  ],
  "functional_domains": [
    "conseil et relation client",
    "gestion administrative"
  ],
  "required_skills": [
    "accueil premium",
    "relation client",
    "réception",
    "organisation"
  ],
  "preferred_skills": [
    "anglais",
    "hôtellerie"
  ],
  "conditions": {},
  "prerequisites": [],
  "source_warning": "La page recrutement de l'employeur confirme l'offre ; elle regroupe plusieurs postes sur une même page.",
  "canonical_offer_id": "sources-caudalie-guest-relation-juillet-2026"
}
