{
  "id": "drfip-assistant-administratif-2026-31706",
  "title": "Assistant administratif au service des impôts des particuliers",
  "employer": "DRFIP Gironde",
  "source_url": "https://choisirleservicepublic.gouv.fr/offre-emploi/MEF_2026-31706/",
  "source_site": "choisirleservicepublic.gouv.fr",
  "source_kind": "direct_employer",
  "verification_status": "active",
  "verification_note": "Page exacte revérifiée pendant le scan full du 22 juillet 2026.",
  "published_at": null,
  "captured_at": "2026-07-22T09:45:53+02:00",
  "last_verified_at": "2026-07-22T09:45:53+02:00",
  "summary": "Accueillir les particuliers, répondre aux questions fiscales, traiter réclamations, déclarations et messages au sein du service des impôts de Bordeaux.",
  "location_label": "Bordeaux",
  "contract_type": "CDD jusqu'au 31 août 2029",
  "full_time": true,
  "sector_labels": [
    "service public",
    "finances publiques"
  ],
  "functional_domains": [
    "conseil et relation client",
    "gestion administrative"
  ],
  "compensation": {
    "minimum": 23551,
    "maximum": 23551,
    "currency": "EUR",
    "period": "year"
  },
  "required_skills": [
    "accueil",
    "relation usager",
    "gestion administrative",
    "maîtrise de soi"
  ],
  "preferred_skills": [],
  "conditions": {},
  "prerequisites": []
}
