{
  "canonical_offer_id": "canonical-offer-8cb4554824f518d6",
  "captured_at": "2026-07-22T19:56:06.775708+02:00",
  "conditions": {},
  "contract_type": "contrat non communiqué",
  "employer": "Département de la Gironde",
  "evidence": [
    {
      "excerpt": "MEDECIN DE PMI SANTE DU JEUNE ENFANT REFERENT.E DE CIRCONSCRIPTION.S LE TEICH",
      "field": "title",
      "locator": "HTML h1 or listing link"
    },
    {
      "excerpt": "Département de la Gironde",
      "field": "employer",
      "locator": "regional source audit"
    }
  ],
  "extraction": {
    "ambiguous_fields": [
      "summary",
      "prerequisites",
      "location_label"
    ],
    "extractor_version": 1,
    "method": "deterministic-html",
    "review_status": "required",
    "source_archive_path": "private/offer-scan-archives/2026-07-22-195606-747817-full/gironde.fr/8cb4554824f518d6fd06.html",
    "source_sha256": "9dbe55e306ed0cbef381d4bd831b46792cadf2631034bcaff4b6e8d02564224c"
  },
  "full_time": null,
  "functional_domains": [
    "conseil et relation client",
    "gestion administrative",
    "gestion et coordination de projets"
  ],
  "id": "offer-61e0d069d26a3b94",
  "industry_sector_ids": [
    "services-publics"
  ],
  "last_verified_at": "2026-07-22T19:56:06.775708+02:00",
  "location_label": "Bègles",
  "preferred_skills": [],
  "prerequisites": [],
  "published_at": null,
  "required_skills": [
    "vente"
  ],
  "sector_labels": [
    "services publics"
  ],
  "source_kind": "direct_employer",
  "source_site": "gironde.fr",
  "source_url": "https://www.gironde.fr/offres-d-emploi/medecin-de-pmi-sante-du-jeune-enfant-referente-de-circonscriptions-le-teich",
  "summary": "Poste de MEDECIN DE PMI SANTE DU JEUNE ENFANT REFERENT.E DE CIRCONSCRIPTION.S LE TEICH proposé par Département de la Gironde à Bègles. La page source a été archivée et doit faire l’objet d’une revue sémantique avant recommandation.",
  "title": "MEDECIN DE PMI SANTE DU JEUNE ENFANT REFERENT.E DE CIRCONSCRIPTION.S LE TEICH",
  "verification_status": "active"
}
